truffles/__init__.py
truffles/context/__init__.py
truffles/context/base.py
truffles/context/exceptions.py
truffles/context/implementations/__init__.py
truffles/context/implementations/memory.py
truffles/context/marker.py
truffles/context/state.py
truffles/core/enhanced.py
truffles/core/tool_manager.py
truffles/enhanced/__init__.py
truffles/enhanced/locator.py
truffles/enhanced/page.py
truffles/models/__init__.py
truffles/models/default_model.py
truffles/models/exceptions.py
truffles/tasks/__init__.py
truffles/tasks/listing_task.py
truffles/tasks/task.py
truffles/tools/__init__.py
truffles/tools/base.py
truffles/tools/list_detector/__init__.py
truffles/tools/list_detector/list_detector.py
truffles/tools/list_detector/strategies/__init__.py
truffles/tools/list_detector/strategies/base.py
truffles/tools/list_detector/strategies/item_strategy.py
truffles/tools/list_detector/strategies/llm_strategy.py
truffles/tools/list_detector/strategies/wrapper_strategy.py
truffles/tools/list_detector/utils.py
truffles/tools/structure_locator/__init__.py
truffles/tools/structure_locator/exceptions.py
truffles/tools/structure_locator/messages.py
truffles/tools/structure_locator/structure_locator.py
truffles/utils/__init__.py
truffles/utils/locator_ops.py
truffles/utils/wrap.py
truffles-0.2.0.dist-info/LICENSE
truffles-0.2.0.dist-info/METADATA
truffles-0.2.0.dist-info/WHEEL
truffles-0.2.0.dist-info/RECORD
