Metadata-Version: 2.1
Name: truffles
Version: 0.2.0
Summary: Tools for data extraction from the web with AI
Author: Shoco Team
Author-email: truffles@shoco.ai
Requires-Python: >=3.9,<4.0
Classifier: Programming Language :: Python :: 3
Classifier: Programming Language :: Python :: 3.9
Classifier: Programming Language :: Python :: 3.10
Classifier: Programming Language :: Python :: 3.11
Classifier: Programming Language :: Python :: 3.12
Classifier: Programming Language :: Python :: 3.13
Requires-Dist: beautifulsoup4 (==4.12.3)
Requires-Dist: langchain (>=0.3.9,<0.4.0)
Requires-Dist: langchain-anthropic (>=0.3.0,<0.4.0)
Requires-Dist: langchain-core (>=0.3.21,<0.4.0)
Requires-Dist: langchain-openai (>=0.2.11,<0.3.0)
Requires-Dist: pillow (>=11.0.0,<12.0.0)
Requires-Dist: playwright (>=1.49.0,<2.0.0)
